{
  "hash": "8f1dfcd71cf3c8033a61ec9ef8b19509",
  "result": {
    "markdown": "---\ntitle: \"Informacion Data set\"\nauthor: \"Brayan Urrejola\"\ndate: \"2023-02-13\"\ncategories: [information]\nimage: \"image.jpg\"\n---\n\n\n### Especificaciones de datos:\n\nEste Data Set contiene datos de pacientes que solo son de mujeres mayores de 21 años de raza indigena Pima.\n\nLa finalidad de estos datos es predecir mediante un diagnostico si un paciente tiene diabetes, basado en ciertas medidas y variables.\n\n| Nombre Columna               | Descripcion                                                                                                           | Tipo de variable |\n|-------------------------|-----------------------------|:----------------:|\n| **Pregnancies**              | Muestra la cantidad de veces que el paciente ha tenido un embarazo, representado con un numero entero.                |     Numerica     |\n| **Glucose**                  | Muestra la cantidad de glucosa en la sangre que contiene el paciente en su cuerpo, representado con un numero entero. |     Numerica     |\n| **BloodPressure**            | Muestra la medida de la presion arterial del paciente, representado con un numero entero.                             |     Numerica     |\n| **SkinThickness**            | Muestra en cantidad el grosor de la piel del paciente, representado con un numero entero.                             |     Numerica     |\n| **Insulin**                  | Muestra la cantidad de insulina en la sangre que tiene el paciente, representado con un numero entero.                |     Numerica     |\n| **BMI (Body mass index)**    | Muestra el indice de masa corporal del paciente, representado con un numero decimal.                                  | Numerica (float) |\n| **DiabetesPedigreeFunction** | Muestra el porcentaje/nivel de Diabetes del paciente, representado con un numero decimal.                             | Numerica (float) |\n| **Age**                      | Muestra la edad del paciente, representado con un numero entero.                                                      |     Numerica     |\n| **Outcome**                  | Muestra el resultado del paciente, indicando \"1\" si tiene diabetes y \"0\" en caso de que no tenga diabetes.            |    Categorica    |\n\n### Tabla de contenidos:\n\n\n::: {.cell}\n\n```{.r .cell-code}\ndiabe <- read.csv(\"C:/Users/braya/Desktop/LIVA/diabetes.csv\")\nhead(diabe)\n```\n\n::: {.cell-output .cell-output-stdout}\n```\n  Pregnancies Glucose BloodPressure SkinThickness Insulin  BMI\n1           6     148            72            35       0 33.6\n2           1      85            66            29       0 26.6\n3           8     183            64             0       0 23.3\n4           1      89            66            23      94 28.1\n5           0     137            40            35     168 43.1\n6           5     116            74             0       0 25.6\n  DiabetesPedigreeFunction Age Outcome\n1                    0.627  50       1\n2                    0.351  31       0\n3                    0.672  32       1\n4                    0.167  21       0\n5                    2.288  33       1\n6                    0.201  30       0\n```\n:::\n:::\n",
    "supporting": [],
    "filters": [
      "rmarkdown/pagebreak.lua"
    ],
    "includes": {},
    "engineDependencies": {},
    "preserve": {},
    "postProcess": true
  }
}